bible_mcp_server/__init__.py
bible_mcp_server/server.py
bible_mcp_server-0.1.0.dist-info/METADATA
bible_mcp_server-0.1.0.dist-info/WHEEL
bible_mcp_server-0.1.0.dist-info/entry_points.txt
bible_mcp_server-0.1.0.dist-info/RECORD
