Metadata-Version: 2.4
Name: bible-mcp-server
Version: 0.1.0
Summary: A comprehensive Bible server providing verse lookup, search, study tools, and devotional content using Bible APIs
Requires-Python: >=3.10
Requires-Dist: fastmcp>=2.0.0
